[
  {
    "name": "ROOTS le petit bar",
    "type": "бар",
    "address": "ул. Блохина, 3/1",
    "lat": 59.9734,
    "lng": 30.2898,
    "isoDate": "2025-10-28",
    "displayDate": "28 октября 2025",
    "desc": "Французский камерный бар с коктейлями и закусками. Уютное место на Петроградке.",
    "link": "https://sobaka.ru/bars/roots-le-petit-bar"
  },
  {
    "name": "Ле Бистро Де Ла Ферм",
    "type": "ресторан",
    "address": "Большая Пушкарская ул., 38",
    "lat": 59.9678,
    "lng": 30.3167,
    "isoDate": "2025-10-20",
    "displayDate": "20 октября 2025",
    "desc": "Французская фермерская кухня: омлет, судак. Открыл Оливье Робер.",
    "link": "https://restoclub.ru/spb/place/le-bistro-de-la-ferm"
  },
  {
    "name": "Ингрия",
    "type": "ресторан",
    "address": "наб. Реки Смоленки, 14",
    "lat": 59.9432,
    "lng": 30.2570,
    "isoDate": "2025-10-15",
    "displayDate": "15 октября 2025",
    "desc": "Северная кухня с локальными продуктами: дичь, сезонные супы.",
    "link": "https://spb.allcafe.ru/place/ingriya"
  },
  {
    "name": "The Legends",
    "type": "бар",
    "address": "Садовая ул., 62",
    "lat": 59.9296,
    "lng": 30.3281,
    "isoDate": "2025-10-10",
    "displayDate": "10 октября 2025",
    "desc": "Рок-бар с джемами и американской кухней: бургеры, коктейли.",
    "link": "https://chef.ru/place/the-legends"
  },
  {
    "name": "Nonino Secret",
    "type": "бар",
    "address": "наб. Фонтанки, 30",
    "lat": 59.9372,
    "lng": 30.3500,
    "isoDate": "2025-10-30",
    "displayDate": "30 октября 2025",
    "desc": "Секретный бар с коктейлями на граппе. Атмосфера 1920-х.",
    "link": "https://restoclub.ru/spb/place/nonino-secret-room"
  },
  {
    "name": "HOOKAH PLACE",
    "type": "кальянная",
    "address": "Полтавская ул., 8",
    "lat": 59.9360,
    "lng": 30.3600,
    "isoDate": "2025-11-05",
    "displayDate": "5 ноября 2025",
    "desc": "Премиум кальян с редкими смесями. Комфортные зоны.",
    "link": "https://hookahplace.ru"
  },
  {
    "name": "Tito Bistro",
    "type": "кафе",
    "address": "Итальянская ул., 6",
    "lat": 59.9338,
    "lng": 30.3452,
    "isoDate": "2025-10-25",
    "displayDate": "25 октября 2025",
    "desc": "Грузинско-итальянская кухня: хачапури, пицца.",
    "link": "https://edagda.ru/spb/tito-bistro"
  },
  {
    "name": "Morii",
    "type": "ресторан",
    "address": "Лиговский пр., 271",
    "lat": 59.9270,
    "lng": 30.3601,
    "isoDate": "2025-10-18",
    "displayDate": "18 октября 2025",
    "desc": "Гастрономия с винами: сезонные меню.",
    "link": "https://restoclub.ru/spb/place/morii"
  },
  {
    "name": "Salty",
    "type": "ресторан",
    "address": "ул. Миргородская, 20",
    "lat": 59.9275,
    "lng": 30.3652,
    "isoDate": "2025-11-03",
    "displayDate": "3 ноября 2025",
    "desc": "Морепродукты: устрицы, крабы.",
    "link": "https://sobaka.ru/bars/salty"
  },
  {
    "name": "Leopold Brasserie & Pub",
    "type": "ресторан",
    "address": "ул. Рубинштейна, 23",
    "lat": 59.9298,
    "lng": 30.3440,
    "isoDate": "2025-11-01",
    "displayDate": "1 ноября 2025",
    "desc": "Бельгийская брассерия: moules-frites, пиво.",
    "link": "https://restoclub.ru/spb/place/leopold"
  },
  {
    "name": "Эссенция",
    "type": "ресторан",
    "address": "Московский пр., 206",
    "lat": 59.8521,
    "lng": 30.3185,
    "isoDate": "2025-11-01",
    "displayDate": "1 ноября 2025",
    "desc": "Молекулярная кухня: инновационные блюда.",
    "link": "https://gastronom.ru/place/essentsiya"
  },
  {
    "name": "Текстура",
    "type": "кафе",
    "address": "Галерный пр., 5",
    "lat": 59.9410,
    "lng": 30.2990,
    "isoDate": "2025-10-29",
    "displayDate": "29 октября 2025",
    "desc": "Художественная студия-кафе с десертами.",
    "link": "https://edagda.ru/spb/tekstura"
  },
  {
    "name": "Винный факультет",
    "type": "бар",
    "address": "ул. Ординарная, 4",
    "lat": 59.9601,
    "lng": 30.2985,
    "isoDate": "2025-10-22",
    "displayDate": "22 октября 2025",
    "desc": "Винный бар с дегустациями.",
    "link": "https://sobaka.ru/bars/vinnyy-fakultet"
  },
  {
    "name": "Китайский бар в Доме Мурузи",
    "type": "бар",
    "address": "Литейный пр., 24",
    "lat": 59.9432,
    "lng": 30.3480,
    "isoDate": "2025-11-01",
    "displayDate": "1 ноября 2025",
    "desc": "Китайская закуска в музее Бродского.",
    "link": "https://sobaka.ru/bars/dom-muruzi"
  },
  {
    "name": "FRANK",
    "type": "ресторан",
    "address": "ул. Рубинштейна, 29/28",
    "lat": 59.9292,
    "lng": 30.3450,
    "isoDate": "2025-10-18",
    "displayDate": "18 октября 2025",
    "desc": "Реберная с американской кухней.",
    "link": "https://restoclub.ru/spb/place/frank"
  },
  {
    "name": "Detstvo Play Cafe",
    "type": "кафе",
    "address": "ул. Марата, 10",
    "lat": 59.9305,
    "lng": 30.3530,
    "isoDate": "2025-11-05",
    "displayDate": "5 ноября 2025",
    "desc": "Семейное кафе с играми для детей.",
    "link": "https://restoclub.ru/spb/place/detstvo-play-cafe"
  },
  {
    "name": "Cyber El",
    "type": "бар",
    "address": "наб. реки Фонтанки, 90",
    "lat": 59.9280,
    "lng": 30.3355,
    "isoDate": "2025-11-08",
    "displayDate": "8 ноября 2025",
    "desc": "Кибер-бар с VR и коктейлями.",
    "link": "https://restoclub.ru/spb/place/cyber-el"
  },
  {
    "name": "Луч",
    "type": "бар",
    "address": "ул. Некрасова, 50",
    "lat": 59.9340,
    "lng": 30.3450,
    "isoDate": "2025-11-01",
    "displayDate": "1 ноября 2025",
    "desc": "Коктейльный бар с авторскими напитками.",
    "link": "https://2gis.ru/spb/firm/70000001045467813"
  }
]
